safedrop/__init__.py
safedrop/app.py
safedrop/lib/fileops.dll
safedrop/lib/fileops.so
safedrop-0.2.8.dist-info/METADATA
safedrop-0.2.8.dist-info/WHEEL
safedrop-0.2.8.dist-info/top_level.txt
safedrop-0.2.8.dist-info/RECORD
