Metadata-Version: 2.4
Name: safedrop
Version: 0.2.8
Summary: The Official Safedrop Package
Author-email: Safedrop <dev@safedrop.com>
License: MIT
Requires-Python: >=3.8
